{
  "title": "My Kowloon Server",
  "description": "My brand new Kowloon server",
  "location": {
    "name": "London, England",
    "type": "Place",
    "latitude": "51.5074456",
    "longitude": "-0.1277653"
  },
  "domain": "kowloon.social",
  "uploadDir": "./uploads",
  "registrationIsOpen": false,
  "maxUploadSize": 100,
  "defaultPronouns": {
    "subject": "they",
    "object": "them",
    "possAdj": "their",
    "possPro": "theirs",
    "reflexive": "themselves"
  },
  "blockedDomains": [],
  "likeEmojis": [
    {
      "name": "React",
      "emoji": "👍"
    },
    {
      "name": "Love",
      "emoji": "❤️"
    },
    {
      "name": "Sad",
      "emoji": "😭"
    },
    {
      "name": "Angry",
      "emoji": "🤬"
    },
    {
      "name": "Shocked",
      "emoji": "😮"
    },
    {
      "name": "Puke",
      "emoji": "🤮"
    }
  ],
  "adminEmail": "admin@kowloon.social",
  "emailServer": {
    "protocol": "smtp",
    "host": "localhost",
    "username": "test",
    "password": "test"
  },
  "icon": "/images/icons/server.png"
}